phacts/__init__.py
phacts/lifestyle.pkl.xz
phacts/linux.fasta35
phacts/load_data.py
phacts/osx.fasta35
phacts-1.8.data/scripts/phacts.py
phacts-1.8.dist-info/LICENSE
phacts-1.8.dist-info/METADATA
phacts-1.8.dist-info/WHEEL
phacts-1.8.dist-info/top_level.txt
phacts-1.8.dist-info/RECORD
