Metadata-Version: 2.1
Name: phacts
Version: 1.8
Summary: A program to predict the lifestyle (virulent/lytic or temperate/lysogenic) of a phage genome
Home-page: https://github.com/deprekate/phacts
Author: Katelyn McNair
Author-email: deprekate@gmail.com
Classifier: Programming Language :: Python :: 3
Classifier: License :: OSI Approved :: GNU General Public License v3 or later (GPLv3+)
Classifier: Operating System :: OS Independent
Requires-Python: >3.5.2
License-File: LICENSE
Requires-Dist: sklearn
Requires-Dist: numpy
Requires-Dist: dill
